verse16/__init__.py
verse16/cli.py
verse16/temp.py
verse16/verse16.py
verse16-0.1.2.dist-info/LICENSE
verse16-0.1.2.dist-info/METADATA
verse16-0.1.2.dist-info/WHEEL
verse16-0.1.2.dist-info/entry_points.txt
verse16-0.1.2.dist-info/top_level.txt
verse16-0.1.2.dist-info/RECORD
