Metadata-Version: 2.1
Name: verse16
Version: 0.1.2
Summary: nlp rap text-generation
Home-page: https://github.com/pelgo14/verse16
Author: pelgo14
Author-email: pelgo14@protonmail.com
License: BSD license
Keywords: verse16 nlp rap text-generation
Platform: UNKNOWN
Classifier: Development Status :: 2 - Pre-Alpha
Classifier: Intended Audience :: Developers
Classifier: License :: OSI Approved :: BSD License
Classifier: Natural Language :: English
Classifier: Programming Language :: Python :: 3
Classifier: Programming Language :: Python :: 3.5
Classifier: Programming Language :: Python :: 3.6
Classifier: Programming Language :: Python :: 3.7
Requires-Python: >=3.5
Requires-Dist: tensorflow-gpu (<=1.15.3)
Requires-Dist: progressbar2
Requires-Dist: pronouncing
Requires-Dist: syllables
Requires-Dist: gpt-2-simple
Requires-Dist: progressist
